ovsgui/__init__.py
ovsgui-1.0.6.dist-info/LICENSE
ovsgui-1.0.6.dist-info/METADATA
ovsgui-1.0.6.dist-info/WHEEL
ovsgui-1.0.6.dist-info/entry_points.txt
ovsgui-1.0.6.dist-info/top_level.txt
ovsgui-1.0.6.dist-info/RECORD
