Metadata-Version: 2.1
Name: ovsgui
Version: 1.0.6
Summary: Online Variable System GUI - A GUI for managing online variables through Firebase
Home-page: https://github.com/e500ky/ovsgui
Author: ArsTech
Author-email: arstechai@gmail.com
Classifier: Programming Language :: Python :: 3
Classifier: License :: OSI Approved :: MIT License
Classifier: Operating System :: OS Independent
Requires-Python: >=3.6
License-File: LICENSE
Requires-Dist: customtkinter>=5.0.0
Requires-Dist: firebase-admin>=6.0.0
Requires-Dist: python-dotenv>=1.0.0
